setup.py
distri_py/Binomialdistribution.py
distri_py/Gaussiandistribution.py
distri_py/Generaldistribution.py
distri_py/__init__.py
distri_py.egg-info/PKG-INFO
distri_py.egg-info/SOURCES.txt
distri_py.egg-info/dependency_links.txt
distri_py.egg-info/not-zip-safe
distri_py.egg-info/top_level.txt